gitvis/__init__.py
gitvis/__main__.py
gitvis/cli.py
gitvis/print_m.py
gitvis/scan.py
gitvis/stats.py
gitvis/utils.py
gitvis-0.1.1.dist-info/LICENSE
gitvis-0.1.1.dist-info/METADATA
gitvis-0.1.1.dist-info/WHEEL
gitvis-0.1.1.dist-info/entry_points.txt
gitvis-0.1.1.dist-info/top_level.txt
gitvis-0.1.1.dist-info/RECORD
